storj_uplink/__init__.py
storj_uplink/access.py
storj_uplink/download.py
storj_uplink/errors.py
storj_uplink/libuplink.so
storj_uplink/module_classes.py
storj_uplink/module_def.py
storj_uplink/project.py
storj_uplink/py.typed
storj_uplink/skeleton.py
storj_uplink/uplink.py
storj_uplink/upload.py
storj_uplink-0.2.0.dist-info/licenses/LICENSE.txt
storj_uplink-0.2.0.dist-info/METADATA
storj_uplink-0.2.0.dist-info/WHEEL
storj_uplink-0.2.0.dist-info/top_level.txt
storj_uplink-0.2.0.dist-info/RECORD
