Metadata-Version: 2.4
Name: storj-uplink
Version: 0.2.0
Summary: Add a short description here!
Home-page: https://github.com/bkjohnson/storj-uplink-python
Author: Brooks Johnson
License: Apache-2.0
Project-URL: Issues, https://github.com/bkjohnson/storj-uplink-python/issues
Platform: any
Classifier: Development Status :: 4 - Beta
Classifier: Programming Language :: Python
License-File: LICENSE.txt
Requires-Dist: importlib-metadata; python_version < "3.8"
Provides-Extra: testing
Requires-Dist: setuptools; extra == "testing"
Requires-Dist: pytest; extra == "testing"
Requires-Dist: pytest-cov; extra == "testing"
Dynamic: license-file
